bluebeam/Engine.py
bluebeam/GlobalVars.py
bluebeam/Level.py
bluebeam/TileMap.py
bluebeam/__init__.py
bluebeam/Sounds/Dangerous Dungeon.wav
bluebeam/Sounds/charge.wav
bluebeam/Sounds/charged.wav
bluebeam/Sounds/charged_shot.wav
bluebeam/Sounds/cherish.xm
bluebeam/Sounds/damaged.wav
bluebeam/Sounds/flc_pamp.mod
bluebeam/Sounds/impact.wav
bluebeam/Sounds/shot.wav
bluebeam/Sounds/trainer5.mod
bluebeam/Sounds/up.wav
bluebeam/images/0.png
bluebeam/images/1.png
bluebeam/images/2.png
bluebeam/images/3.png
bluebeam/images/CreditsButton.png
bluebeam/images/CreditsButtonGlow.png
bluebeam/images/DeathScreen.png
bluebeam/images/HelpButton.png
bluebeam/images/HelpButtonGlow.png
bluebeam/images/MenuButton.png
bluebeam/images/MenuButtonRed.png
bluebeam/images/Options2.png
bluebeam/images/OptionsButton.png
bluebeam/images/OptionsButtonGlow.png
bluebeam/images/Pause.png
bluebeam/images/PauseMenu.png
bluebeam/images/QuitButton.png
bluebeam/images/QuitButtonGlow.png
bluebeam/images/QuitButtonRed.png
bluebeam/images/RestartButton.png
bluebeam/images/RestartButtonRed.png
bluebeam/images/SelectionArrow.png
bluebeam/images/StartButton.png
bluebeam/images/StartButtonGlow.png
bluebeam/images/StartButtonRed.png
bluebeam/images/arm.png
bluebeam/images/ball.png
bluebeam/images/boss01_commander.png
bluebeam/images/boss01_core.png
bluebeam/images/boss01_turrets.png
bluebeam/images/commander_gun.png
bluebeam/images/heart.png
bluebeam/images/sigma.png
bluebeam/images/testHUD.png
bluebeam/images/testHUD2.png
bluebeam/images/test_background.png
bluebeam/images/Blue/frame 1.png
bluebeam/images/Blue/frame 2.png
bluebeam/images/Blue/frame 3.png
bluebeam/images/Blue/frame 4.png
bluebeam/images/Blue/frame 5.png
bluebeam/images/Blue/frame 6.png
bluebeam/images/Enemy/fish-big1.png
bluebeam/images/Enemy/fish-big2.png
bluebeam/images/Enemy/fish-big3.png
bluebeam/images/Enemy/fish-big4.png
bluebeam/images/Enemy/shooter1.png
bluebeam/images/Enemy/shooter2.png
bluebeam/images/Enemy/shooter3.png
bluebeam_beta-0.0.2.dist-info/LICENSE
bluebeam_beta-0.0.2.dist-info/METADATA
bluebeam_beta-0.0.2.dist-info/WHEEL
bluebeam_beta-0.0.2.dist-info/entry_points.txt
bluebeam_beta-0.0.2.dist-info/top_level.txt
bluebeam_beta-0.0.2.dist-info/RECORD
