Metadata-Version: 2.1
Name: bluebeam-beta
Version: 0.0.2
Summary: A side scroller, tile map, shooter game
Home-page: UNKNOWN
Author: Clyde Slichter
Author-email: cnslichter@ufl.edu
License: UNKNOWN
Keywords: pygame,game,shooter
Platform: UNKNOWN
Requires-Python: >=3.9
License-File: LICENSE
Requires-Dist: pygame (>=2.0.1)
Requires-Dist: PyTMX (>=3.25)
Requires-Dist: wheel
